kdetools/__init__.py
kdetools/kde.py
kdetools/kdecdf.py
kdetools-0.2.2.dist-info/METADATA
kdetools-0.2.2.dist-info/WHEEL
kdetools-0.2.2.dist-info/licenses/LICENSE
kdetools-0.2.2.dist-info/RECORD
