Metadata-Version: 2.4
Name: kdetools
Version: 0.2.2
Summary: Kernel Density Estimation tools and functions
Project-URL: Homepage, https://github.com/MutaharChalmers/kdetools
Author-email: Mutahar Chalmers <mutahar.chalmers@gmail.com>
License: MIT License
License-File: LICENSE
Classifier: Development Status :: 4 - Beta
Classifier: Intended Audience :: Science/Research
Classifier: License :: OSI Approved :: MIT License
Classifier: Operating System :: OS Independent
Classifier: Programming Language :: Python :: 3
Classifier: Topic :: Scientific/Engineering
Requires-Python: >=3.8
Requires-Dist: numpy>=1.18
Requires-Dist: pyarrow>=10.0
Requires-Dist: scipy>=1.10
